{
  "m": {
    "guildId": "760222722919497820",
    "joinedTimestamp": 1655036505082,
    "premiumSinceTimestamp": null,
    "nickname": null,
    "pending": false,
    "communicationDisabledUntilTimestamp": null,
    "userId": "351129866877403145",
    "avatar": null,
    "displayName": "Dazzu",
    "roles": [
      "956172112790433842",
      "760222722919497820"
    ],
    "avatarURL": null,
    "displayAvatarURL": "https://cdn.discordapp.com/avatars/351129866877403145/4fe316cbc8863679fb8a67bce04fb2a8.webp"
  },
  "roles": [
    {
      "guild": "760222722919497820",
      "icon": null,
      "unicodeEmoji": null,
      "id": "956172112790433842",
      "name": "WTS-Cooldown",
      "color": 0,
      "hoist": false,
      "rawPosition": 5,
      "permissions": "1071698529856",
      "managed": false,
      "mentionable": false,
      "tags": {},
      "createdTimestamp": 1648039596508
    },
    {
      "guild": "760222722919497820",
      "icon": null,
      "unicodeEmoji": null,
      "id": "760222722919497820",
      "name": "@everyone",
      "color": 0,
      "hoist": false,
      "rawPosition": 0,
      "permissions": "1071698529856",
      "managed": false,
      "mentionable": false,
      "tags": {},
      "createdTimestamp": 1601321621399
    }
  ]
}