[{"name":"mixed-trades","amount":501},{"name":"equipment","amount":2534},{"name":"costumes","amount":4317},{"name":"helm-back","amount":897},{"name":"helm-front","amount":1990},{"name":"helm-side","amount":1390},{"name":"helm-top","amount":2339},{"name":"armor-aura","amount":642},{"name":"armor-ankle","amount":113},{"name":"armor-back","amount":1534},{"name":"armor-front","amount":1849},{"name":"armor-rear","amount":506},{"name":"miscellaneous","amount":1701},{"name":"Sprite Food","amount":169},{"name":"Materials","amount":243}]